snipty/__init__.py
snipty/base.py
snipty/command.py
snipty/downloaders.py
snipty-0.9.1.data/scripts/snipty
snipty-0.9.1.dist-info/LICENSE
snipty-0.9.1.dist-info/METADATA
snipty-0.9.1.dist-info/WHEEL
snipty-0.9.1.dist-info/top_level.txt
snipty-0.9.1.dist-info/RECORD
