Metadata-Version: 2.1
Name: snipty
Version: 0.9.1
Summary: Track snippets use in your codebase with ease
Home-page: https://github.com/cypreess/snipty
Author: Kris Dorosz
Author-email: cypreess@gmail.com
License: MIT
Platform: UNKNOWN
Classifier: Programming Language :: Python :: 3
Classifier: License :: OSI Approved :: MIT License
Classifier: Operating System :: OS Independent
Requires-Python: >3.6
Requires-Dist: requests (>=2.18)
Requires-Dist: termcolor (>=1.1.0)
Requires-Dist: PyYAML (>=3.13)
